radiant/compiler/__init__.py
radiant/compiler/server.py
radiant/compiler/android/__init__.py
radiant/compiler/android/permissions.py
radiant_compiler-0.1a5.data/scripts/radiant_p4a
radiant_compiler-0.1a5.dist-info/LICENSE
radiant_compiler-0.1a5.dist-info/METADATA
radiant_compiler-0.1a5.dist-info/WHEEL
radiant_compiler-0.1a5.dist-info/top_level.txt
radiant_compiler-0.1a5.dist-info/RECORD
