Metadata-Version: 2.1
Name: radiant-compiler
Version: 0.1a5
Summary: Brython Framework
Download-URL: https://github.com/dunderlab/python-radiant.compiler
Author: Yeison Cardona
Author-email: yencardonaal@unal.edu.co
Maintainer: Yeison Cardona
Maintainer-email: yencardonaal@unal.edu.co
License: BSD-2-Clause
Classifier: Development Status :: 4 - Beta
Classifier: License :: OSI Approved :: BSD License
Classifier: Programming Language :: Python :: 3.10
Classifier: Programming Language :: Python :: 3.9
Classifier: Programming Language :: Python :: 3.8
Requires-Python: >=3.8
License-File: LICENSE
Requires-Dist: python-for-android
Requires-Dist: cython
